{
	"name": "PL_CopyDynamicfile_Timestamp",
	"properties": {
		"activities": [
			{
				"name": "Copy data Dynamic timestamp",
				"type": "Copy",
				"dependsOn": [],
				"policy": {
					"timeout": "7.00:00:00",
					"retry": 0,
					"retryIntervalInSeconds": 30,
					"secureOutput": false,
					"secureInput": false
				},
				"userProperties": [],
				"typeProperties": {
					"source": {
						"type": "DelimitedTextSource",
						"storeSettings": {
							"type": "AzureBlobStorageReadSettings",
							"recursive": true,
							"enablePartitionDiscovery": false
						},
						"formatSettings": {
							"type": "DelimitedTextReadSettings"
						}
					},
					"sink": {
						"type": "DelimitedTextSink",
						"storeSettings": {
							"type": "AzureBlobStorageWriteSettings"
						},
						"formatSettings": {
							"type": "DelimitedTextWriteSettings",
							"quoteAllText": true,
							"fileExtension": ".txt"
						}
					},
					"enableStaging": false,
					"translator": {
						"type": "TabularTranslator",
						"typeConversion": true,
						"typeConversionSettings": {
							"allowDataTruncation": true,
							"treatBooleanAsNumber": false
						}
					}
				},
				"inputs": [
					{
						"referenceName": "DS_storage_sasatyav2_source_dynamiccopy",
						"type": "DatasetReference",
						"parameters": {
							"DatasetFileName": {
								"value": "@pipeline().parameters.FileName",
								"type": "Expression"
							}
						}
					}
				],
				"outputs": [
					{
						"referenceName": "DS_Storage_sssatyav2_Target_timestamp",
						"type": "DatasetReference",
						"parameters": {
							"Filename": {
								"value": "@pipeline().parameters.FileName",
								"type": "Expression"
							}
						}
					}
				]
			}
		],
		"parameters": {
			"FileName": {
				"type": "string"
			}
		},
		"annotations": [],
		"lastPublishTime": "2022-07-21T04:43:28Z"
	},
	"type": "Microsoft.DataFactory/factories/pipelines"
}